onnx2onnx/__init__.py
onnx2onnx/__main__.py
onnx2onnx/checker.py
onnx2onnx/graph.py
onnx2onnx/pass_manager.py
onnx2onnx/evaluator/__init__.py
onnx2onnx/passes/__init__.py
onnx2onnx/passes/convert.py
onnx2onnx/passes/optimize.py
onnx2onnx/passes/pattern.py
onnx2onnx/passes/quantize.py
onnx2onnx/passes/rewriter.py
onnx2onnx/passes/transforms.py
onnx2onnx/passes/utils.py
onnx2onnx-0.3.3.dist-info/entry_points.txt
onnx2onnx-0.3.3.dist-info/LICENSE
onnx2onnx-0.3.3.dist-info/WHEEL
onnx2onnx-0.3.3.dist-info/METADATA
onnx2onnx-0.3.3.dist-info/RECORD
